mdv/__init__.py
mdv/__main__.py
mdv/cli.py
mdv/file_response.py
mdv/file_tree.py
mdv/file_types.py
mdv/media_streaming.py
mdv/models.py
mdv/path_security.py
mdv/rendering.py
mdv/server.py
mdv/state.py
mdv/watcher.py
mdv/websocket_manager.py
mdv/static/app.js
mdv/static/favicon.ico
mdv/static/index.html
mdv/static/styles.css
tests/__init__.py
tests/test_server.py
mdv_live-0.2.10.dist-info/METADATA
mdv_live-0.2.10.dist-info/WHEEL
mdv_live-0.2.10.dist-info/entry_points.txt
mdv_live-0.2.10.dist-info/top_level.txt
mdv_live-0.2.10.dist-info/RECORD
