Metadata-Version: 2.4
Name: mdv-live
Version: 0.2.10
Summary: Markdown Viewer - File tree + Live preview + Hot reload
Author-email: PanHouse <hirono.okamoto@panhouse.jp>
License: MIT
Project-URL: Homepage, https://github.com/panhouse/mdv
Project-URL: Repository, https://github.com/panhouse/mdv
Keywords: markdown,viewer,live-reload,preview,hot-reload
Classifier: Development Status :: 4 - Beta
Classifier: Environment :: Console
Classifier: Environment :: Web Environment
Classifier: Intended Audience :: Developers
Classifier: License :: OSI Approved :: MIT License
Classifier: Programming Language :: Python :: 3
Classifier: Programming Language :: Python :: 3.9
Classifier: Programming Language :: Python :: 3.10
Classifier: Programming Language :: Python :: 3.11
Classifier: Programming Language :: Python :: 3.12
Classifier: Topic :: Text Processing :: Markup :: Markdown
Requires-Python: >=3.9
Requires-Dist: fastapi>=0.104.0
Requires-Dist: uvicorn>=0.24.0
Requires-Dist: websockets>=12.0
Requires-Dist: markdown-it-py>=3.0.0
Requires-Dist: mdit-py-plugins>=0.4.0
Requires-Dist: python-multipart>=0.0.6
